spaceprime/__init__.py
spaceprime/analysis.py
spaceprime/cli.py
spaceprime/demography.py
spaceprime/plot.py
spaceprime/simulation.py
spaceprime/utilities.py
spaceprime/data/localities.geojson
spaceprime/data/projections.tif
spaceprime-0.0.5.dist-info/LICENSE
spaceprime-0.0.5.dist-info/METADATA
spaceprime-0.0.5.dist-info/WHEEL
spaceprime-0.0.5.dist-info/entry_points.txt
spaceprime-0.0.5.dist-info/top_level.txt
spaceprime-0.0.5.dist-info/RECORD
