Metadata-Version: 2.1
Name: spaceprime
Version: 0.0.5
Summary: A python package to facilitate spatially explicit coalescent modeling in msprime
Author-email: Connor French <french.connor.m@gmail.com>
License: MIT License
Project-URL: Homepage, https://github.com/connor-french/spaceprime
Keywords: spaceprime
Classifier: Intended Audience :: Developers
Classifier: License :: OSI Approved :: MIT License
Classifier: Natural Language :: English
Classifier: Programming Language :: Python :: 3.8
Classifier: Programming Language :: Python :: 3.9
Classifier: Programming Language :: Python :: 3.10
Classifier: Programming Language :: Python :: 3.11
Classifier: Programming Language :: Python :: 3.12
Requires-Python: >=3.8
License-File: LICENSE
Requires-Dist: numpy <2
Requires-Dist: typing
Requires-Dist: msprime
Requires-Dist: rasterio >=1.0.0
Requires-Dist: scipy
Requires-Dist: shapely
Requires-Dist: geopandas
Requires-Dist: scikit-allel
Requires-Dist: contextily
Requires-Dist: matplotlib
Requires-Dist: folium
Requires-Dist: mapclassify
Requires-Dist: esda >=2.5.1
Requires-Dist: libpysal >=4.10
Requires-Dist: scikit-learn
Requires-Dist: pandas
Provides-Extra: all
Requires-Dist: spaceprime[analysis] ; extra == 'all'
Provides-Extra: analysis
Requires-Dist: esda >=2.5.1 ; extra == 'analysis'
Requires-Dist: libpysal >=4.10 ; extra == 'analysis'
Requires-Dist: sklearn ; extra == 'analysis'
Requires-Dist: itertools ; extra == 'analysis'
Requires-Dist: pandas ; extra == 'analysis'
